indonesian_ai_assistant/__init__.py
indonesian_ai_assistant/assistant.py
indonesian_ai_assistant-1.0.dist-info/METADATA
indonesian_ai_assistant-1.0.dist-info/WHEEL
indonesian_ai_assistant-1.0.dist-info/top_level.txt
indonesian_ai_assistant-1.0.dist-info/RECORD
