Metadata-Version: 2.1
Name: indonesian-ai-assistant
Version: 1.0
Summary: A virtual assistant that recognizes speech and responds in Indonesian.
Author: Althaf Sachio Zaidan
Classifier: Programming Language :: Python :: 3
Classifier: License :: OSI Approved :: MIT License
Classifier: Operating System :: OS Independent
Requires-Dist: SpeechRecognition
Requires-Dist: pyttsx3
Requires-Dist: PyAudio
